__init__.py
dbt_switch/__init__.py
dbt_switch/main.py
dbt_switch/cli/__init__.py
dbt_switch/cli/parser.py
dbt_switch/config/__init__.py
dbt_switch/config/cloud_handler.py
dbt_switch/config/file_handler.py
dbt_switch/config/input_handler.py
dbt_switch/utils/__init__.py
dbt_switch/utils/logger.py
dbt_switch/utils/version_check.py
dbt_switch/validation/__init__.py
dbt_switch/validation/helpers.py
dbt_switch/validation/schemas.py
dbt_switch-0.2.6.dist-info/METADATA
dbt_switch-0.2.6.dist-info/WHEEL
dbt_switch-0.2.6.dist-info/entry_points.txt
dbt_switch-0.2.6.dist-info/top_level.txt
dbt_switch-0.2.6.dist-info/RECORD
