Metadata-Version: 2.4
Name: dbt-switch
Version: 0.2.6
Summary: A simple CLI to switch between dbt Cloud projects and hosts.
Requires-Python: >=3.9
Requires-Dist: click>=8.1.8
Requires-Dist: pydantic>=2.10.6
Requires-Dist: pyyaml>=6.0.2
